rfc2xml/__init__.py
rfc2xml/__main__.py
rfc2xml/grammar.txt
rfc2xml/rfc2xml.py
rfc2xml/xmlable.py
rfc2xml/elements/__init__.py
rfc2xml/elements/abstract.py
rfc2xml/elements/artwork.py
rfc2xml/elements/author.py
rfc2xml/elements/back.py
rfc2xml/elements/date.py
rfc2xml/elements/element.py
rfc2xml/elements/figure.py
rfc2xml/elements/front.py
rfc2xml/elements/list.py
rfc2xml/elements/middle.py
rfc2xml/elements/note.py
rfc2xml/elements/organization.py
rfc2xml/elements/rfc.py
rfc2xml/elements/section.py
rfc2xml/elements/t.py
rfc2xml/elements/title.py
rfc2xml/elements/toc.py
rfc2xml/elements/toc_item.py
rfc2xml/elements/workgroup.py
rfc2xml/elements/xref.py
rfc2xml-0.1.2.dist-info/LICENSE.md
rfc2xml-0.1.2.dist-info/METADATA
rfc2xml-0.1.2.dist-info/WHEEL
rfc2xml-0.1.2.dist-info/top_level.txt
rfc2xml-0.1.2.dist-info/RECORD
