Metadata-Version: 2.1
Name: rfc2xml
Version: 0.1.2
Summary: Tool to process an RFC or Internet Standard into XML. Structure can also be accessed directly within a seperate Python project.
Home-page: https://bitbucket.org/davidksouthgate/rfc2xml/
Author: David Southgate
Author-email: d@davidsouthgate.co.uk
License: UNKNOWN
Platform: UNKNOWN
Classifier: Programming Language :: Python :: 3
Classifier: License :: OSI Approved :: MIT License
Classifier: Operating System :: OS Independent
Requires-Dist: parsley
Requires-Dist: lxml
